odoo/addons/sale_order_template_notes/LICENSE
odoo/addons/sale_order_template_notes/README.rst
odoo/addons/sale_order_template_notes/__init__.py
odoo/addons/sale_order_template_notes/__manifest__.py
odoo/addons/sale_order_template_notes/images/screen.png
odoo/addons/sale_order_template_notes/models/__init__.py
odoo/addons/sale_order_template_notes/models/sale_order.py
odoo/addons/sale_order_template_notes/models/sale_order_template.py
odoo/addons/sale_order_template_notes/static/description/icon.png
odoo/addons/sale_order_template_notes/static/description/index.html
odoo/addons/sale_order_template_notes/tests/TEST_INSTRUCTIONS.rst
odoo/addons/sale_order_template_notes/views/sale_order_template.xml
odoo_addon_sale_order_template_notes-16.0.1.0.0.dist-info/METADATA
odoo_addon_sale_order_template_notes-16.0.1.0.0.dist-info/WHEEL
odoo_addon_sale_order_template_notes-16.0.1.0.0.dist-info/top_level.txt
odoo_addon_sale_order_template_notes-16.0.1.0.0.dist-info/RECORD
